{
    "Seminar 3: Business Practices for Design & Eco-Social Innovation": {
        "lecturer": "Reifer G\u00fcnther",
        "type": "LECT",
        "last_update": 1558294028.1806633,
        "title": "Seminar 3: Business Practices for Design & Eco-Social Innovation"
    },
    "Research methods PhD-Montali": {
        "lecturer": "Montali Marco",
        "type": "LECT",
        "last_update": 1558294028.180643,
        "title": "Research methods PhD-Montali"
    },
    "Exam1 27042 Mathematics for PPE M1+M2": {
        "lecturer": "Maraner Paolo",
        "type": "EXAM",
        "last_update": 1558294028.1805403,
        "title": "Exam1 27042 Mathematics for PPE M1+M2"
    },
    "Chemometric approaches to study the chemical and sensory markers of food processing": {
        "lecturer": "Longo Edoardo",
        "type": "LECT",
        "last_update": 1558294028.1806648,
        "title": "Chemometric approaches to study the chemical and sensory markers of food processing"
    },
    "Data Curation M2: Data Profiling": {
        "lecturer": "Cristani Marco",
        "type": "LECT",
        "last_update": 1558294028.1807232,
        "title": "Data Curation M2: Data Profiling"
    },
    "Analisi Matematica II": {
        "lecturer": "Bertotti Maria Letizia",
        "type": "EXERCISE",
        "last_update": 1558294028.180682,
        "title": "Analisi Matematica II"
    },
    "Agricultural Systems in Mountan Areas_Livestock management in mountain aereas": {
        "lecturer": "Gauly Matthias",
        "type": "LECT",
        "last_update": 1558294028.1805632,
        "title": "Agricultural Systems in Mountan Areas_Livestock management in mountain aereas"
    },
    "Fisica Tecnica": {
        "lecturer": "Baratieri Marco",
        "type": "EXERCISE",
        "last_update": 1558294028.18059,
        "title": "Fisica Tecnica"
    },
    "Building HVAC Systems": {
        "lecturer": "Baggio Paolo",
        "type": "LECT",
        "last_update": 1558294028.1807826,
        "title": "Building HVAC Systems"
    },
    "Real-Time Big Data Processing": {
        "lecturer": "Xiao Guohui",
        "type": "LECT",
        "last_update": 1558294028.1806967,
        "title": "Real-Time Big Data Processing"
    },
    "Reaction kinetics in food processing": {
        "lecturer": "Scampicchio Matteo Mario",
        "type": "LECT",
        "last_update": 1558294028.1806664,
        "title": "Reaction kinetics in food processing"
    },
    "Botanik_Prof.Zerbe": {
        "lecturer": "Zerbe Stefan",
        "type": "LECT",
        "last_update": 1558294028.1805427,
        "title": "Botanik_Prof.Zerbe"
    },
    "Formal Languages and Compilers": {
        "lecturer": "Artale Alessandro",
        "type": "LAB",
        "last_update": 1558294028.1807008,
        "title": "Formal Languages and Compilers"
    },
    "Purchasing and Supply Management": {
        "lecturer": "Zanoni Simone",
        "type": "LECT",
        "last_update": 1558294028.1806684,
        "title": "Purchasing and Supply Management"
    },
    "Biochemistry and physiology of agricultural plants_Group_B": {
        "lecturer": "Cesco Stefano",
        "type": "EXERCISE",
        "last_update": 1558294028.1806622,
        "title": "Biochemistry and physiology of agricultural plants_Group_B"
    },
    "Information Security/System Security (EMSE-ATSE)": {
        "lecturer": "Molinari Andrea",
        "type": "LECT",
        "last_update": 1558294028.18063,
        "title": "Information Security/System Security (EMSE-ATSE)"
    },
    "Agricultural Systems in Mountan Areas_Mountain Agriculture": {
        "lecturer": "Zanotelli Damiano",
        "type": "LECT",
        "last_update": 1558294028.1805463,
        "title": "Agricultural Systems in Mountan Areas_Mountain Agriculture"
    },
    "Disegno e Metodi dell' Ingegneria Industriale_L-9": {
        "lecturer": "Borgianni Yuri",
        "type": "LECT",
        "last_update": 1558294028.1807585,
        "title": "Disegno e Metodi dell' Ingegneria Industriale_L-9"
    },
    "The natural microbial starters for innovation and authenticity ": {
        "lecturer": "Di Cagno Raffaella",
        "type": "LECT",
        "last_update": 1558294028.1805623,
        "title": "The natural microbial starters for innovation and authenticity "
    },
    "Real-Time Big Data Processing Lab": {
        "lecturer": "Xiao Guohui",
        "type": "LAB",
        "last_update": 1558294028.18068,
        "title": "Real-Time Big Data Processing Lab"
    },
    "Introduzione all'intelligenza emotiva": {
        "lecturer": "Tokarchuk Oksana",
        "type": "LECT",
        "last_update": 1558294028.1805491,
        "title": "Introduzione all'intelligenza emotiva"
    },
    "Silviculture and grassland management": {
        "lecturer": "Peratoner Giovanni",
        "type": "LECT",
        "last_update": 1558294028.1805496,
        "title": "Silviculture and grassland management"
    },
    "Italiano Tecnico": {
        "lecturer": "Cagol Marco",
        "type": "LECT",
        "last_update": 1558294028.180761,
        "title": "Italiano Tecnico"
    },
    "Biochemistry and physiology of agricultural plants": {
        "lecturer": "Cesco Stefano",
        "type": "EXAM",
        "last_update": 1558294028.180575,
        "title": "Biochemistry and physiology of agricultural plants"
    },
    "Advanced methods for fluid machine design_Muhasilovic": {
        "lecturer": "Muhasilovic Medzid",
        "type": "LECT",
        "last_update": 1558294028.1807816,
        "title": "Advanced methods for fluid machine design_Muhasilovic"
    },
    "Ecosystem Restoration and rural appraisal_Ecosystem Restoration": {
        "lecturer": "Zerbe Stefan",
        "type": "LECT",
        "last_update": 1558294028.1807432,
        "title": "Ecosystem Restoration and rural appraisal_Ecosystem Restoration"
    },
    "Forest planning and protection forestry_Forest harvesting and logistics": {
        "lecturer": "Gallo Raimondo",
        "type": "LECT",
        "last_update": 1558294028.180731,
        "title": "Forest planning and protection forestry_Forest harvesting and logistics"
    },
    "Web & Media Design": {
        "lecturer": "Moretti Matteo Maria",
        "type": "LECT",
        "last_update": 1558294028.1807177,
        "title": "Web & Media Design"
    },
    "Design & Production": {
        "lecturer": "Ugur Yavuz Secil",
        "type": "LECT",
        "last_update": 1558294028.1807172,
        "title": "Design & Production"
    },
    "Microbiologia Agroambientale e Industrie Agrarie": {
        "lecturer": "Brusetti Lorenzo",
        "type": "EXAM",
        "last_update": 1558294028.1805573,
        "title": "Microbiologia Agroambientale e Industrie Agrarie"
    },
    "Analytische Chemie f\u00fcr Agrarprodukte und Lebensmittel": {
        "lecturer": "Mimmo Tanja",
        "type": "EXERCISE",
        "last_update": 1558294028.1806865,
        "title": "Analytische Chemie f\u00fcr Agrarprodukte und Lebensmittel"
    },
    "Chimica organica": {
        "lecturer": "Benini Stefano",
        "type": "LECT",
        "last_update": 1558294028.1807272,
        "title": "Chimica organica"
    },
    "Fluidmechanik": {
        "lecturer": "Larcher Michele",
        "type": "EXERCISE",
        "last_update": 1558294028.1807508,
        "title": "Fluidmechanik"
    },
    "Fruit Production and Viticulture": {
        "lecturer": "Andreotti Carlo",
        "type": "LECT",
        "last_update": 1558294028.1807096,
        "title": "Fruit Production and Viticulture"
    },
    "Programming Project": {
        "lecturer": "Tkalcic Marko",
        "type": "LECT",
        "last_update": 1558294028.1806939,
        "title": "Programming Project"
    },
    "Nature conservation and management_Applied botany": {
        "lecturer": "Wellstein Camilla",
        "type": "LECT",
        "last_update": 1558294028.1807506,
        "title": "Nature conservation and management_Applied botany"
    },
    "EXAM 1-25400 Advanced Financial Statement Analysis": {
        "lecturer": "Bonacchi Massimiliano",
        "type": "EXAM",
        "last_update": 1558294028.1805618,
        "title": "EXAM 1-25400 Advanced Financial Statement Analysis"
    },
    "Physics": {
        "lecturer": "Petti Luisa",
        "type": "LECT",
        "last_update": 1558294028.1806884,
        "title": "Physics"
    },
    "Physik I": {
        "lecturer": "Peer Angelika",
        "type": "EXERCISE",
        "last_update": 1558294028.1807253,
        "title": "Physik I"
    },
    "Technisches Deutsch": {
        "lecturer": "Cavosi Renata",
        "type": "LECT",
        "last_update": 1558294028.1806931,
        "title": "Technisches Deutsch"
    },
    "Industrieanlagen und Arbeitssicherheit": {
        "lecturer": "Dallasega Patrick",
        "type": "EXERCISE",
        "last_update": 1558294028.180741,
        "title": "Industrieanlagen und Arbeitssicherheit"
    },
    "Project Management and Professional Ethics": {
        "lecturer": "Janes Andrea Alexander",
        "type": "LECT",
        "last_update": 1558294028.1805663,
        "title": "Project Management and Professional Ethics"
    },
    "Verification and Validation (EMSE-VV-8) / Software Reliability and Testing": {
        "lecturer": "Russo Barbara",
        "type": "LECT",
        "last_update": 1558294028.1807323,
        "title": "Verification and Validation (EMSE-VV-8) / Software Reliability and Testing"
    },
    "E1-27205 Quantitative Finance": {
        "lecturer": "Boreiko Dmitri",
        "type": "EXAM",
        "last_update": 1558294028.1805673,
        "title": "E1-27205 Quantitative Finance"
    },
    "29023_Paper Writing, Publication and Review Process": {
        "lecturer": "Grimpe Christoph",
        "type": "LECT",
        "last_update": 1558294028.180588,
        "title": "29023_Paper Writing, Publication and Review Process"
    },
    "Management of mountain rivers_Hydromorphology_of_mountain_rivers": {
        "lecturer": "Comiti Francesco",
        "type": "LECT",
        "last_update": 1558294028.1807032,
        "title": "Management of mountain rivers_Hydromorphology_of_mountain_rivers"
    },
    "Elettrotecnica/Macchine elettriche": {
        "lecturer": "Bottesi Omar",
        "type": "EXERCISE",
        "last_update": 1558294028.1807296,
        "title": "Elettrotecnica/Macchine elettriche"
    },
    "Industrial Automation and Mechatronics II": {
        "lecturer": "Calligaro Sandro",
        "type": "LECT",
        "last_update": 1558294028.180758,
        "title": "Industrial Automation and Mechatronics II"
    },
    "Agrarrecht": {
        "lecturer": "Miribung Georg",
        "type": "LECT",
        "last_update": 1558294028.1807654,
        "title": "Agrarrecht"
    },
    "Programming Project EX A": {
        "lecturer": "Souza Cardoso Evellin Cristine",
        "type": "LAB",
        "last_update": 1558294028.1806834,
        "title": "Programming Project EX A"
    },
    "Programming Project EX B": {
        "lecturer": "Billero Riccardo",
        "type": "LAB",
        "last_update": 1558294028.1806843,
        "title": "Programming Project EX B"
    },
    "Fundamentals of programming": {
        "lecturer": "Troquard Nicolas",
        "type": "LECT",
        "last_update": 1558294028.180762,
        "title": "Fundamentals of programming"
    },
    "Sustainable development of mountain areas_Economic development of rural areas": {
        "lecturer": "Fischer Christian Diethard",
        "type": "LECT",
        "last_update": 1558294028.1806958,
        "title": "Sustainable development of mountain areas_Economic development of rural areas"
    },
    "Advanced Applications of Building Physics": {
        "lecturer": "Gasparella Andrea",
        "type": "LECT",
        "last_update": 1558294028.180753,
        "title": "Advanced Applications of Building Physics"
    },
    "EXAM 1-27036 Banking and Corporate Finance": {
        "lecturer": "Murgia Maurizio",
        "type": "EXAM",
        "last_update": 1558294028.1805754,
        "title": "EXAM 1-27036 Banking and Corporate Finance"
    },
    "Game Theory PhD": {
        "lecturer": "Porello Daniele",
        "type": "LECT",
        "last_update": 1558294028.1807022,
        "title": "Game Theory PhD"
    },
    "Botanik_Alle_Studierende": {
        "lecturer": "Wellstein Camilla",
        "type": "EXERCISE",
        "last_update": 1558294028.1805766,
        "title": "Botanik_Alle_Studierende"
    },
    "Silviculture_Ventura": {
        "lecturer": "Ventura Maurizio",
        "type": "LECT",
        "last_update": 1558294028.180578,
        "title": "Silviculture_Ventura"
    },
    "Database Management Systems LAB A": {
        "lecturer": "Barbieri Verena",
        "type": "LAB",
        "last_update": 1558294028.1805785,
        "title": "Database Management Systems LAB A"
    },
    "Data Integration Lab / Data Curation M1: Data Integration Lab": {
        "lecturer": "Calvanese Diego",
        "type": "LAB",
        "last_update": 1558294028.180712,
        "title": "Data Integration Lab / Data Curation M1: Data Integration Lab"
    },
    "Energetics": {
        "lecturer": "Baratieri Marco",
        "type": "EXERCISE",
        "last_update": 1558294028.1805801,
        "title": "Energetics"
    },
    "Rural Technology Systems": {
        "lecturer": "Mazzetto Fabrizio",
        "type": "EXERCISE",
        "last_update": 1558294028.180737,
        "title": "Rural Technology Systems"
    },
    "Agricultural Economics and Policy": {
        "lecturer": "Fischer Christian Diethard",
        "type": "LECT",
        "last_update": 1558294028.1807876,
        "title": "Agricultural Economics and Policy"
    },
    "Database Management Systems LAB B": {
        "lecturer": "Dign\u00f6s Anton",
        "type": "LAB",
        "last_update": 1558294028.1805818,
        "title": "Database Management Systems LAB B"
    },
    "Electric Power Conversion Equipment": {
        "lecturer": "Calligaro Sandro",
        "type": "LECT",
        "last_update": 1558294028.1807406,
        "title": "Electric Power Conversion Equipment"
    },
    "Web and Internet Engineering": {
        "lecturer": "Zanker Markus",
        "type": "LECT",
        "last_update": 1558294028.1807306,
        "title": "Web and Internet Engineering"
    },
    "Management of mountain rivers_Flood risk mitigation": {
        "lecturer": "Comiti Francesco",
        "type": "EXERCISE",
        "last_update": 1558294028.1806123,
        "title": "Management of mountain rivers_Flood risk mitigation"
    },
    "English Specialized": {
        "lecturer": "Prior Jemma F.",
        "type": "LECT",
        "last_update": 1558294028.1807148,
        "title": "English Specialized"
    },
    "Applications of fluid mechanics to energy engineering": {
        "lecturer": "Muhasilovic Medzid",
        "type": "EXERCISE",
        "last_update": 1558294028.1807482,
        "title": "Applications of fluid mechanics to energy engineering"
    },
    "Information Security/System Security EMSE-ATSE_LAB": {
        "lecturer": "El Ioini Nabil",
        "type": "LAB",
        "last_update": 1558294028.1805885,
        "title": "Information Security/System Security EMSE-ATSE_LAB"
    },
    "Food-human axis: the gut microbiome": {
        "lecturer": "Gobbetti Marco",
        "type": "LECT",
        "last_update": 1558294028.1805892,
        "title": "Food-human axis: the gut microbiome"
    },
    "Produktionsplanung und \u2013steuerung": {
        "lecturer": "Ratschiller Roland",
        "type": "EXERCISE",
        "last_update": 1558294028.180635,
        "title": "Produktionsplanung und \u2013steuerung"
    },
    "Artificial Intelligence": {
        "lecturer": "Rivkin Andrey",
        "type": "LAB",
        "last_update": 1558294028.1807868,
        "title": "Artificial Intelligence"
    },
    "Machine Construction and Design": {
        "lecturer": "Gorla Carlo",
        "type": "EXERCISE",
        "last_update": 1558294028.1806355,
        "title": "Machine Construction and Design"
    },
    "Mathematics II- MOD 1- Analysis": {
        "lecturer": "Tillo Tammam",
        "type": "LECT",
        "last_update": 1558294028.1807237,
        "title": "Mathematics II- MOD 1- Analysis"
    },
    "Food chemistry": {
        "lecturer": "Mannino Saverio",
        "type": "EXERCISE",
        "last_update": 1558294028.1806858,
        "title": "Food chemistry"
    },
    "English Specialized_AGR": {
        "lecturer": "Prior Jemma F.",
        "type": "EXERCISE",
        "last_update": 1558294028.1807246,
        "title": "English Specialized_AGR"
    },
    "Sustainable development of mountain areas_Sustainable tourism and regional products": {
        "lecturer": "Fischer Christian Diethard",
        "type": "LECT",
        "last_update": 1558294028.1807241,
        "title": "Sustainable development of mountain areas_Sustainable tourism and regional products"
    },
    "Empirical Software Engineering Research (EMSE-ESER 8)": {
        "lecturer": "Fronza Ilenia",
        "type": "LECT",
        "last_update": 1558294028.1807709,
        "title": "Empirical Software Engineering Research (EMSE-ESER 8)"
    },
    "Empirical Software Engineering Research (EMSE-ESER 8) ": {
        "lecturer": "Susanj Boris",
        "type": "LAB",
        "last_update": 1558294028.1807258,
        "title": "Empirical Software Engineering Research (EMSE-ESER 8) "
    },
    "Database Management Systems": {
        "lecturer": "Dign\u00f6s Anton",
        "type": "LECT",
        "last_update": 1558294028.1807501,
        "title": "Database Management Systems"
    },
    "Exam1 -27075_ Principi e laboratorio del Diritto Amministrativo": {
        "lecturer": "De Bellis Maurizia",
        "type": "EXAM",
        "last_update": 1558294028.1805997,
        "title": "Exam1 -27075_ Principi e laboratorio del Diritto Amministrativo"
    },
    "Data Curation M2: Data Profiling Lab": {
        "lecturer": "Cristani Marco",
        "type": "LAB",
        "last_update": 1558294028.18073,
        "title": "Data Curation M2: Data Profiling Lab"
    },
    "Cultural Anthropology": {
        "lecturer": "Tauber Elisabeth",
        "type": "LECT",
        "last_update": 1558294028.180674,
        "title": "Cultural Anthropology"
    },
    "Ecosystem Restoration and rural appraisal_Rural appraisal": {
        "lecturer": "Masiero Mauro",
        "type": "LECT",
        "last_update": 1558294028.1807292,
        "title": "Ecosystem Restoration and rural appraisal_Rural appraisal"
    },
    "German Supplementary course": {
        "lecturer": "Gallo Daniel",
        "type": "LECT",
        "last_update": 1558294028.1807315,
        "title": "German Supplementary course"
    },
    "Web and Text Mining": {
        "lecturer": "Ozaki Rivera Castillo Ana Helena",
        "type": "LECT",
        "last_update": 1558294028.1807752,
        "title": "Web and Text Mining"
    },
    "L-Diskurse zum Kulturerbe": {
        "lecturer": "Gl\u00fcher Gerhard",
        "type": "LECT",
        "last_update": 1558294028.1807384,
        "title": "L-Diskurse zum Kulturerbe"
    },
    "Computer Systems MOD 2-Operating Systems": {
        "lecturer": "Persia Fabio",
        "type": "LECT",
        "last_update": 1558294028.1807785,
        "title": "Computer Systems MOD 2-Operating Systems"
    },
    "Deutsch im Studium 1 (Design)": {
        "lecturer": "Widmann Brigitte",
        "type": "LECT",
        "last_update": 1558294028.180608,
        "title": "Deutsch im Studium 1 (Design)"
    },
    "Machine Learning": {
        "lecturer": "Kacimi El Hassani Mouna",
        "type": "LECT",
        "last_update": 1558294028.1807783,
        "title": "Machine Learning"
    },
    "Presentation, Communication and Scientific Writing": {
        "lecturer": "Fronza Ilenia",
        "type": "LECT",
        "last_update": 1558294028.1807437,
        "title": "Presentation, Communication and Scientific Writing"
    },
    "History of Design 2": {
        "lecturer": "H\u00f6ger Hans Leo",
        "type": "LECT",
        "last_update": 1558294028.1807442,
        "title": "History of Design 2"
    },
    "Zoologie": {
        "lecturer": "Gauly Matthias",
        "type": "EXERCISE",
        "last_update": 1558294028.18079,
        "title": "Zoologie"
    },
    "Biochemistry and physiology of agricultural plants_Group_C": {
        "lecturer": "Cesco Stefano",
        "type": "EXERCISE",
        "last_update": 1558294028.1806746,
        "title": "Biochemistry and physiology of agricultural plants_Group_C"
    },
    "Testdaf-Pr\u00fcfung": {
        "lecturer": " Nickenig Christoph",
        "type": "EXAM",
        "last_update": 1558294028.1806142,
        "title": "Testdaf-Pr\u00fcfung"
    },
    "Fachsprache Deutsch": {
        "lecturer": "Cavosi Renata",
        "type": "LECT",
        "last_update": 1558294028.1807513,
        "title": "Fachsprache Deutsch"
    },
    "Mathematics II- MOD 2- Computational Math.": {
        "lecturer": "Carpentieri Bruno",
        "type": "LECT",
        "last_update": 1558294028.1806166,
        "title": "Mathematics II- MOD 2- Computational Math."
    },
    "Exam1-27064 Principi e laboratorio d. diritto pubblico e d. fonti normative": {
        "lecturer": "Baroncelli Stefania",
        "type": "EXAM",
        "last_update": 1558294028.1806192,
        "title": "Exam1-27064 Principi e laboratorio d. diritto pubblico e d. fonti normative"
    },
    "Operations research": {
        "lecturer": "Morandi Valentina",
        "type": "LECT",
        "last_update": 1558294028.1806183,
        "title": "Operations research"
    },
    "Verification and Validation (EMSE-VV-8) / Software Reliability and Testing LAB": {
        "lecturer": "Russo Barbara",
        "type": "LAB",
        "last_update": 1558294028.1807473,
        "title": "Verification and Validation (EMSE-VV-8) / Software Reliability and Testing LAB"
    },
    "Electrochemical energy storage and conversion": {
        "lecturer": "Della Volpe Claudio",
        "type": "LECT",
        "last_update": 1558294028.1807606,
        "title": "Electrochemical energy storage and conversion"
    },
    "Web and Text Mining Lab": {
        "lecturer": "Ozaki Rivera Castillo Ana Helena",
        "type": "LAB",
        "last_update": 1558294028.1807463,
        "title": "Web and Text Mining Lab"
    },
    "Storia dell'arte contemporanea 2": {
        "lecturer": "De Cecco Emanuela",
        "type": "LECT",
        "last_update": 1558294028.1807535,
        "title": "Storia dell'arte contemporanea 2"
    },
    "Interface Design": {
        "lecturer": "Schubert Jennifer Liesbeth",
        "type": "LECT",
        "last_update": 1558294028.180765,
        "title": "Interface Design"
    },
    "English Specialised for Design 2 / Foreign language DES-ART 3": {
        "lecturer": "Prior Jemma F.",
        "type": "LECT",
        "last_update": 1558294028.1807551,
        "title": "English Specialised for Design 2 / Foreign language DES-ART 3"
    },
    "Deutsch im Studium 2 (Design) / Fremdsprache DES-ART 2": {
        "lecturer": "Oberhammer Margit",
        "type": "LECT",
        "last_update": 1558294028.1807547,
        "title": "Deutsch im Studium 2 (Design) / Fremdsprache DES-ART 2"
    },
    "Fisica": {
        "lecturer": "Salasnich Luca",
        "type": "LECT",
        "last_update": 1558294028.180742,
        "title": "Fisica"
    },
    "E1_27115_Diritto contrattuale": {
        "lecturer": "Valle Laura",
        "type": "EXAM",
        "last_update": 1558294028.1806254,
        "title": "E1_27115_Diritto contrattuale"
    },
    "Advanced geomatics and environmental impact assessment_Advanced_Geomatics": {
        "lecturer": "Antonello Andrea",
        "type": "EXERCISE",
        "last_update": 1558294028.180769,
        "title": "Advanced geomatics and environmental impact assessment_Advanced_Geomatics"
    },
    "Programming Data Infrastructures": {
        "lecturer": "Savkovic Ognjen",
        "type": "LECT",
        "last_update": 1558294028.1807952,
        "title": "Programming Data Infrastructures"
    },
    "Computer Systems MOD 2-Operating Systems Ex A": {
        "lecturer": "Persia Fabio",
        "type": "LAB",
        "last_update": 1558294028.1807601,
        "title": "Computer Systems MOD 2-Operating Systems Ex A"
    },
    "Computer Systems MOD 2-Operating Systems Ex B": {
        "lecturer": "D'Auria Daniela",
        "type": "LAB",
        "last_update": 1558294028.1807575,
        "title": "Computer Systems MOD 2-Operating Systems Ex B"
    },
    "Web & Communication Design": {
        "lecturer": "Bonetti Emanuele",
        "type": "LECT",
        "last_update": 1558294028.1807632,
        "title": "Web & Communication Design"
    },
    "Biochemistry and physiology of agricultural plants_Group_A": {
        "lecturer": "Cesco Stefano",
        "type": "EXERCISE",
        "last_update": 1558294028.1806314,
        "title": "Biochemistry and physiology of agricultural plants_Group_A"
    },
    "Interior & Exhibit Design": {
        "lecturer": "Gigliotti Roberto",
        "type": "LECT",
        "last_update": 1558294028.1807644,
        "title": "Interior & Exhibit Design"
    },
    "Planning and Simulation of Production and Logistics Systems": {
        "lecturer": "Rauch Erwin",
        "type": "LECT",
        "last_update": 1558294028.1806328,
        "title": "Planning and Simulation of Production and Logistics Systems"
    },
    "E3-27165_Wine Economics": {
        "lecturer": "Schamel G\u00fcnter",
        "type": "EXAM",
        "last_update": 1558294028.180634,
        "title": "E3-27165_Wine Economics"
    },
    "Programming Data Infrastructures Lab": {
        "lecturer": "Savkovic Ognjen",
        "type": "LAB",
        "last_update": 1558294028.180768,
        "title": "Programming Data Infrastructures Lab"
    },
    "Einf\u00fchrung in die Unternehmensf\u00fchrung II": {
        "lecturer": "Lechner Christian Manfred",
        "type": "LECT",
        "last_update": 1558294028.1807704,
        "title": "Einf\u00fchrung in die Unternehmensf\u00fchrung II"
    },
    "Italiano specialistico per Design 1": {
        "lecturer": "Giglio Alessandra",
        "type": "LECT",
        "last_update": 1558294028.1807723,
        "title": "Italiano specialistico per Design 1"
    },
    "Ecologia agraria e principi di agronomia": {
        "lecturer": "Tagliavini Massimo",
        "type": "LECT",
        "last_update": 1558294028.1807468,
        "title": "Ecologia agraria e principi di agronomia"
    },
    "Building HVAC Systems ": {
        "lecturer": "Prada Alessandro",
        "type": "LECT",
        "last_update": 1558294028.1807747,
        "title": "Building HVAC Systems "
    },
    "English Specialised for Design 1": {
        "lecturer": "Prior Jemma F.",
        "type": "LECT",
        "last_update": 1558294028.1807714,
        "title": "English Specialised for Design 1"
    },
    "PLM Product Life Cycle Management": {
        "lecturer": "Franzellin Vittorio",
        "type": "EXERCISE",
        "last_update": 1558294028.1806421,
        "title": "PLM Product Life Cycle Management"
    },
    "Agricultural and Forest Entomology_Group_A": {
        "lecturer": "Angeli Sergio",
        "type": "EXERCISE",
        "last_update": 1558294028.1806426,
        "title": "Agricultural and Forest Entomology_Group_A"
    },
    "Exam2_27092_L' attivit\u00e0 contrattuale delle pubbliche ammin.(M1 + M2)": {
        "lecturer": "Valle Laura",
        "type": "EXAM",
        "last_update": 1558294028.180647,
        "title": "Exam2_27092_L' attivit\u00e0 contrattuale delle pubbliche ammin.(M1 + M2)"
    },
    "Estimo generale e speciale": {
        "lecturer": "Cipolotti Giovanni Battista",
        "type": "EXERCISE",
        "last_update": 1558294028.1807895,
        "title": "Estimo generale e speciale"
    },
    "Exam 1_27003_Introduzione ordinamenti giuridici (M1 diritto pubblico + M2 diritto privato)": {
        "lecturer": "Rosini Monica",
        "type": "EXAM",
        "last_update": 1558294028.1806498,
        "title": "Exam 1_27003_Introduzione ordinamenti giuridici (M1 diritto pubblico + M2 diritto privato)"
    },
    "EXAM 1- 25418 Data Analytics, Big Data and Blockchain": {
        "lecturer": "Coletti Paolo",
        "type": "EXAM",
        "last_update": 1558294028.1806493,
        "title": "EXAM 1- 25418 Data Analytics, Big Data and Blockchain"
    },
    "Exam 2_27096_Istituzioni di diritto privato (Erasmus)": {
        "lecturer": "Valle Laura",
        "type": "EXAM",
        "last_update": 1558294028.1806502,
        "title": "Exam 2_27096_Istituzioni di diritto privato (Erasmus)"
    },
    "Theory of media and cultural consumption": {
        "lecturer": "Mattozzi Alvise",
        "type": "LECT",
        "last_update": 1558294028.180785,
        "title": "Theory of media and cultural consumption"
    },
    "Exam2 27199 Public Economics": {
        "lecturer": "Stillman Steven Eric",
        "type": "EXAM",
        "last_update": 1558294028.1806567,
        "title": "Exam2 27199 Public Economics"
    },
    "Agricultural Economics, Policy, Agrarrecht": {
        "lecturer": "Fischer Christian Diethard",
        "type": "EXAM",
        "last_update": 1558294028.1806533,
        "title": "Agricultural Economics, Policy, Agrarrecht"
    },
    "Mathematics II- MOD 1- Analysis EX B": {
        "lecturer": "Ugolini Simone",
        "type": "EXERCISE",
        "last_update": 1558294028.180653,
        "title": "Mathematics II- MOD 1- Analysis EX B"
    },
    "Exam2 27059 Public Economics": {
        "lecturer": "Schamel G\u00fcnter",
        "type": "EXAM",
        "last_update": 1558294028.1806576,
        "title": "Exam2 27059 Public Economics"
    },
    "Exam 2_27095_Istituzioni di diritto pubblico (Erasmus)": {
        "lecturer": "Rosini Monica",
        "type": "EXAM",
        "last_update": 1558294028.1806557,
        "title": "Exam 2_27095_Istituzioni di diritto pubblico (Erasmus)"
    },
    "Exam2 25286 Public Economics A (PPE 5099": {
        "lecturer": "Stillman Steven Eric",
        "type": "EXAM",
        "last_update": 1558294028.180658,
        "title": "Exam2 25286 Public Economics A (PPE 5099"
    },
    "Mathematics II- MOD 1- Analysis EX A": {
        "lecturer": "Tillo Tammam",
        "type": "EXERCISE",
        "last_update": 1558294028.1806571,
        "title": "Mathematics II- MOD 1- Analysis EX A"
    },
    "Machine Learning Lab": {
        "lecturer": "Kacimi El Hassani Mouna",
        "type": "LAB",
        "last_update": 1558294028.1807854,
        "title": "Machine Learning Lab"
    },
    "Video and Post-production": {
        "lecturer": "Mattuzzi  Francesco",
        "type": "LECT",
        "last_update": 1558294028.180797,
        "title": "Video and Post-production"
    },
    "Responsabilit\u00e0 giuridica e approfondimenti normativi": {
        "lecturer": "Emanuele Otello",
        "type": "LECT",
        "last_update": 1558294028.1806602,
        "title": "Responsabilit\u00e0 giuridica e approfondimenti normativi"
    },
    "Interventi non strutturali di mitigazione": {
        "lecturer": "Righetti Maurizio",
        "type": "EXAM",
        "last_update": 1558294028.1806607,
        "title": "Interventi non strutturali di mitigazione"
    },
    "Aspetti di accessibilit\u00e0 sociale del rischio": {
        "lecturer": "Pedoth Lydia",
        "type": "LECT",
        "last_update": 1558294028.1806614,
        "title": "Aspetti di accessibilit\u00e0 sociale del rischio"
    },
    "Research methods PhD-Franconi": {
        "lecturer": "Franconi Enrico",
        "type": "LECT",
        "last_update": 1558294028.1807451,
        "title": "Research methods PhD-Franconi"
    },
    "Mobile Robotics": {
        "lecturer": "von Ellenrieder Karl Dietrich",
        "type": "EXERCISE",
        "last_update": 1558294028.1807935,
        "title": "Mobile Robotics"
    },
    "27001 Economics 1": {
        "lecturer": "Moradi Alexander",
        "type": "LECT",
        "last_update": 1558294028.180666,
        "title": "27001 Economics 1"
    },
    "27044 Allgemeine Betriebswirtschaftslehre": {
        "lecturer": "Rohloff Michael Wilhelm",
        "type": "LECT",
        "last_update": 1558294028.1807616,
        "title": "27044 Allgemeine Betriebswirtschaftslehre"
    },
    "Genetik und Nutzpflanzenzucht": {
        "lecturer": "Baric Sanja",
        "type": "EXERCISE",
        "last_update": 1558294028.1806755,
        "title": "Genetik und Nutzpflanzenzucht"
    },
    "27200 Environmental and Resource Economics": {
        "lecturer": "Rogna Marco",
        "type": "EXERCISE",
        "last_update": 1558294028.180791,
        "title": "27200 Environmental and Resource Economics"
    },
    "L-27030_ Konsumentenverhalten": {
        "lecturer": "Aichner Thomas",
        "type": "LECT",
        "last_update": 1558294028.180779,
        "title": "L-27030_ Konsumentenverhalten"
    },
    "27065 Public Economics": {
        "lecturer": "Stillman Steven Eric",
        "type": "LECT",
        "last_update": 1558294028.180728,
        "title": "27065 Public Economics"
    },
    "L-29016 PHD Qualitative Research Methods": {
        "lecturer": "De Massis Alfredo Vittorio",
        "type": "LECT",
        "last_update": 1558294028.180675,
        "title": "L-29016 PHD Qualitative Research Methods"
    },
    "27002_Mathematics for Economists_M2_Group 1": {
        "lecturer": "Maraner Paolo",
        "type": "LAB",
        "last_update": 1558294028.1807666,
        "title": "27002_Mathematics for Economists_M2_Group 1"
    },
    "27028-International Marketing": {
        "lecturer": "Veglio Valerio",
        "type": "LECT",
        "last_update": 1558294028.1807365,
        "title": "27028-International Marketing"
    },
    "27048 European Law M2 (European and Public Law)": {
        "lecturer": "Al\u00ec Antonino Giovanni",
        "type": "LECT",
        "last_update": 1558294028.1807542,
        "title": "27048 European Law M2 (European and Public Law)"
    },
    "27037 Economics 1 for PPE": {
        "lecturer": "Santos-Arteaga Francisco Javier",
        "type": "EXERCISE",
        "last_update": 1558294028.180786,
        "title": "27037 Economics 1 for PPE"
    },
    "EXE-Gr1-27006 Information Systems and Data Management_Poiesi": {
        "lecturer": "Poiesi Fabio",
        "type": "EXERCISE",
        "last_update": 1558294028.180789,
        "title": "EXE-Gr1-27006 Information Systems and Data Management_Poiesi"
    },
    "27058 Politica economica per SES": {
        "lecturer": "Tonin Mirco",
        "type": "LECT",
        "last_update": 1558294028.1807477,
        "title": "27058 Politica economica per SES"
    },
    "Forest planning and protection forestry_Forest inventories": {
        "lecturer": "Ventura Maurizio",
        "type": "EXERCISE",
        "last_update": 1558294028.1806874,
        "title": "Forest planning and protection forestry_Forest inventories"
    },
    "27069 Messung der Performance im \u00f6ffentlichen Rechnungswesen": {
        "lecturer": "Piber Martin Christoph",
        "type": "LECT",
        "last_update": 1558294028.1807153,
        "title": "27069 Messung der Performance im \u00f6ffentlichen Rechnungswesen"
    },
    "27060 Finanzm\u00e4rkte und Institutionen f\u00fcr \u00d6S": {
        "lecturer": "Weissensteiner Alex",
        "type": "LECT",
        "last_update": 1558294028.18078,
        "title": "27060 Finanzm\u00e4rkte und Institutionen f\u00fcr \u00d6S"
    },
    "EXE-Gr2-27006 Information Systems and Data Management_Poiesi": {
        "lecturer": "Poiesi Fabio",
        "type": "EXERCISE",
        "last_update": 1558294028.1807845,
        "title": "EXE-Gr2-27006 Information Systems and Data Management_Poiesi"
    },
    "Forest planning and protection forestry_Protection forestry": {
        "lecturer": "Tonon Giustino",
        "type": "LECT",
        "last_update": 1558294028.1806986,
        "title": "Forest planning and protection forestry_Protection forestry"
    },
    "25404 Diritto Commerciale (corso progredito)": {
        "lecturer": "Giudici Paolo",
        "type": "LECT",
        "last_update": 1558294028.1807458,
        "title": "25404 Diritto Commerciale (corso progredito)"
    },
    "27050 Political Science 2": {
        "lecturer": "Farneti Roberto",
        "type": "LECT",
        "last_update": 1558294028.1807659,
        "title": "27050 Political Science 2"
    },
    "27210 Principles of Philosophy 1": {
        "lecturer": "De Gennaro Ivo",
        "type": "EXERCISE",
        "last_update": 1558294028.1807523,
        "title": "27210 Principles of Philosophy 1"
    },
    "27169_M2 Diritto delle autonomie (Diritto regionale e delle autonomie)": {
        "lecturer": "Rosini Monica",
        "type": "LECT",
        "last_update": 1558294028.1807625,
        "title": "27169_M2 Diritto delle autonomie (Diritto regionale e delle autonomie)"
    },
    "Advanced applications of fluid mechanics": {
        "lecturer": "Pisaturo Giuseppe Roberto",
        "type": "EXERCISE",
        "last_update": 1558294028.1807115,
        "title": "Advanced applications of fluid mechanics"
    },
    "Advanced applications of fluid mechanics_Righetti": {
        "lecturer": "Righetti Maurizio",
        "type": "EXERCISE",
        "last_update": 1558294028.1807134,
        "title": "Advanced applications of fluid mechanics_Righetti"
    },
    "27062  Personal und Organisation im \u00f6ffentlichen Sektor M2": {
        "lecturer": "Gunkel Marjaana",
        "type": "LECT",
        "last_update": 1558294028.1807415,
        "title": "27062  Personal und Organisation im \u00f6ffentlichen Sektor M2"
    },
    "27160 Theory of International Relations": {
        "lecturer": "Farneti Roberto",
        "type": "LECT",
        "last_update": 1558294028.1807883,
        "title": "27160 Theory of International Relations"
    },
    "27085_Agstner_Diritto industriale e dei contratti bancari e finanziari": {
        "lecturer": "Agstner Peter",
        "type": "LECT",
        "last_update": 1558294028.1807222,
        "title": "27085_Agstner_Diritto industriale e dei contratti bancari e finanziari"
    },
    "L-27175 M1 Grundlagen des Entrepreneurship (Entrepr.&Unternehmensf\u00fchrung)": {
        "lecturer": "Lechner Christian Manfred",
        "type": "LECT",
        "last_update": 1558294028.1807764,
        "title": "L-27175 M1 Grundlagen des Entrepreneurship (Entrepr.&Unternehmensf\u00fchrung)"
    },
    "Agricultural and Forest Entomology": {
        "lecturer": "Angeli Sergio",
        "type": "LECT",
        "last_update": 1558294028.180734,
        "title": "Agricultural and Forest Entomology"
    },
    "27002_Mathematics for Economists_M2_Group 2": {
        "lecturer": "Maraner Paolo",
        "type": "LAB",
        "last_update": 1558294028.1807947,
        "title": "27002_Mathematics for Economists_M2_Group 2"
    },
    "Planning and Simulation of Production  and Logistics Systems": {
        "lecturer": "Ferretti Ivan",
        "type": "EXERCISE",
        "last_update": 1558294028.1807795,
        "title": "Planning and Simulation of Production  and Logistics Systems"
    },
    "L-27013_Marketing ": {
        "lecturer": "Raich Frieda",
        "type": "LECT",
        "last_update": 1558294028.180782,
        "title": "L-27013_Marketing "
    },
    "27006-Information Systems and Data Management": {
        "lecturer": "Molinari Andrea",
        "type": "LECT",
        "last_update": 1558294028.180757,
        "title": "27006-Information Systems and Data Management"
    },
    "Media Studies": {
        "lecturer": "Metzner-Szigeth Andreas Bernhard Josef",
        "type": "LECT",
        "last_update": 1558294028.1807773,
        "title": "Media Studies"
    },
    "EXE-27013 Marketing ": {
        "lecturer": "H\u00e4rtel Klaus Rudolf Paul",
        "type": "LECT",
        "last_update": 1558294028.1807675,
        "title": "EXE-27013 Marketing "
    },
    "CAD Fundamentals_Becattini": {
        "lecturer": "Becattini Niccol\u00f2",
        "type": "LECT",
        "last_update": 1558294028.1807864,
        "title": "CAD Fundamentals_Becattini"
    },
    "27011_Volkswirtschaftslehre 2": {
        "lecturer": "Gruber Stefan",
        "type": "EXERCISE",
        "last_update": 1558294028.1807737,
        "title": "27011_Volkswirtschaftslehre 2"
    },
    "Agricultural and Forest Entomology_Group_B": {
        "lecturer": "Angeli Sergio",
        "type": "EXERCISE",
        "last_update": 1558294028.1807756,
        "title": "Agricultural and Forest Entomology_Group_B"
    },
    "esame: flash scrivere": {
        "lecturer": " Boscolo Cristina",
        "type": "EXAM",
        "last_update": 1558294028.1807923,
        "title": "esame: flash scrivere"
    },
    "History and Criticism of Film and Audiovisual Media": {
        "lecturer": "Duarte Pe\u00f1aranda German Andres",
        "type": "LECT",
        "last_update": 1558294028.180784,
        "title": "History and Criticism of Film and Audiovisual Media"
    },
    "Tecniche di comunicazione del rischio": {
        "lecturer": "Pedoth Lydia",
        "type": "LECT",
        "last_update": 1558294028.1807914,
        "title": "Tecniche di comunicazione del rischio"
    },
    "Artistic Photography": {
        "lecturer": "Graziani Stefano",
        "type": "LECT",
        "last_update": 1558294028.1807919,
        "title": "Artistic Photography"
    },
    "27026-Auditing": {
        "lecturer": "Mainardi Marco",
        "type": "LECT",
        "last_update": 1558294028.1807966,
        "title": "27026-Auditing"
    },
    "L_27230 Service Design": {
        "lecturer": "Rothbucher Bernhard Heinrich",
        "type": "LECT",
        "last_update": 1558294028.1807961,
        "title": "L_27230 Service Design"
    }
}